<?xml version="1.0" encoding="UTF-8" standalone="yes"?>
<migration xmlns="http://ebean-orm.github.io/xml/ns/dbmigration">
    <changeSet type="apply">
        <addColumn tableName="marker">
            <column name="complete_address" type="varchar(255)"/>
        </addColumn>
        <createTable name="marker_vote" pkName="pk_marker_vote">
            <column name="id" type="bigint" primaryKey="true"/>
            <column name="user_id" type="bigint" notnull="true" references="guide_user.id" foreignKeyName="fk_marker_vote_user_id" foreignKeyIndex="ix_marker_vote_user_id"/>
            <column name="marker_id" type="bigint" notnull="true" references="marker.id" foreignKeyName="fk_marker_vote_marker_id" foreignKeyIndex="ix_marker_vote_marker_id"/>
        </createTable>
    </changeSet>
    <changeSet type="pendingDrops">
        <dropTable name="comment"/>
    </changeSet>
</migration>